shady_island/__init__.py
shady_island/py.typed
shady_island/_jsii/__init__.py
shady_island/_jsii/shady-island@0.1.76.jsii.tgz
shady_island/automation/__init__.py
shady_island/configuration/__init__.py
shady_island/networking/__init__.py
shady_island/servers/__init__.py
shady_island-0.1.76.dist-info/LICENSE
shady_island-0.1.76.dist-info/METADATA
shady_island-0.1.76.dist-info/WHEEL
shady_island-0.1.76.dist-info/top_level.txt
shady_island-0.1.76.dist-info/RECORD
